sopel_bucket/__init__.py
sopel_bucket/bucket.py
sopel_bucket-2.0.2.dist-info/licenses/LICENSE
sopel_bucket-2.0.2.dist-info/METADATA
sopel_bucket-2.0.2.dist-info/WHEEL
sopel_bucket-2.0.2.dist-info/entry_points.txt
sopel_bucket-2.0.2.dist-info/top_level.txt
sopel_bucket-2.0.2.dist-info/RECORD
